{
  "Name": "CLASS06_040_05",
  "Items": [
    {
      "Height": 95,
      "Length": 77,
      "Demand": 1,
      "Value": 7315,
      "Reference": 1
    },
    {
      "Height": 50,
      "Length": 53,
      "Demand": 1,
      "Value": 2650,
      "Reference": 2
    },
    {
      "Height": 11,
      "Length": 30,
      "Demand": 1,
      "Value": 330,
      "Reference": 3
    },
    {
      "Height": 100,
      "Length": 95,
      "Demand": 1,
      "Value": 9500,
      "Reference": 4
    },
    {
      "Height": 73,
      "Length": 73,
      "Demand": 1,
      "Value": 5329,
      "Reference": 5
    },
    {
      "Height": 19,
      "Length": 18,
      "Demand": 1,
      "Value": 342,
      "Reference": 6
    },
    {
      "Height": 60,
      "Length": 19,
      "Demand": 1,
      "Value": 1140,
      "Reference": 7
    },
    {
      "Height": 52,
      "Length": 99,
      "Demand": 1,
      "Value": 5148,
      "Reference": 8
    },
    {
      "Height": 83,
      "Length": 12,
      "Demand": 1,
      "Value": 996,
      "Reference": 9
    },
    {
      "Height": 76,
      "Length": 49,
      "Demand": 1,
      "Value": 3724,
      "Reference": 10
    },
    {
      "Height": 87,
      "Length": 30,
      "Demand": 1,
      "Value": 2610,
      "Reference": 11
    },
    {
      "Height": 3,
      "Length": 13,
      "Demand": 1,
      "Value": 39,
      "Reference": 12
    },
    {
      "Height": 48,
      "Length": 84,
      "Demand": 1,
      "Value": 4032,
      "Reference": 13
    },
    {
      "Height": 77,
      "Length": 68,
      "Demand": 1,
      "Value": 5236,
      "Reference": 14
    },
    {
      "Height": 79,
      "Length": 19,
      "Demand": 1,
      "Value": 1501,
      "Reference": 15
    },
    {
      "Height": 76,
      "Length": 26,
      "Demand": 1,
      "Value": 1976,
      "Reference": 16
    },
    {
      "Height": 24,
      "Length": 11,
      "Demand": 1,
      "Value": 264,
      "Reference": 17
    },
    {
      "Height": 11,
      "Length": 31,
      "Demand": 1,
      "Value": 341,
      "Reference": 18
    },
    {
      "Height": 60,
      "Length": 73,
      "Demand": 1,
      "Value": 4380,
      "Reference": 19
    },
    {
      "Height": 26,
      "Length": 60,
      "Demand": 1,
      "Value": 1560,
      "Reference": 20
    },
    {
      "Height": 99,
      "Length": 48,
      "Demand": 1,
      "Value": 4752,
      "Reference": 21
    },
    {
      "Height": 99,
      "Length": 26,
      "Demand": 1,
      "Value": 2574,
      "Reference": 22
    },
    {
      "Height": 84,
      "Length": 15,
      "Demand": 1,
      "Value": 1260,
      "Reference": 23
    },
    {
      "Height": 42,
      "Length": 72,
      "Demand": 1,
      "Value": 3024,
      "Reference": 24
    },
    {
      "Height": 95,
      "Length": 85,
      "Demand": 1,
      "Value": 8075,
      "Reference": 25
    },
    {
      "Height": 98,
      "Length": 76,
      "Demand": 1,
      "Value": 7448,
      "Reference": 26
    },
    {
      "Height": 41,
      "Length": 1,
      "Demand": 1,
      "Value": 41,
      "Reference": 27
    },
    {
      "Height": 46,
      "Length": 49,
      "Demand": 1,
      "Value": 2254,
      "Reference": 28
    },
    {
      "Height": 68,
      "Length": 42,
      "Demand": 1,
      "Value": 2856,
      "Reference": 29
    },
    {
      "Height": 96,
      "Length": 36,
      "Demand": 1,
      "Value": 3456,
      "Reference": 30
    },
    {
      "Height": 53,
      "Length": 20,
      "Demand": 1,
      "Value": 1060,
      "Reference": 31
    },
    {
      "Height": 94,
      "Length": 15,
      "Demand": 1,
      "Value": 1410,
      "Reference": 32
    },
    {
      "Height": 7,
      "Length": 77,
      "Demand": 1,
      "Value": 539,
      "Reference": 33
    },
    {
      "Height": 16,
      "Length": 96,
      "Demand": 1,
      "Value": 1536,
      "Reference": 34
    },
    {
      "Height": 75,
      "Length": 93,
      "Demand": 1,
      "Value": 6975,
      "Reference": 35
    },
    {
      "Height": 74,
      "Length": 24,
      "Demand": 1,
      "Value": 1776,
      "Reference": 36
    },
    {
      "Height": 34,
      "Length": 78,
      "Demand": 1,
      "Value": 2652,
      "Reference": 37
    },
    {
      "Height": 12,
      "Length": 77,
      "Demand": 1,
      "Value": 924,
      "Reference": 38
    },
    {
      "Height": 96,
      "Length": 77,
      "Demand": 1,
      "Value": 7392,
      "Reference": 39
    },
    {
      "Height": 9,
      "Length": 66,
      "Demand": 1,
      "Value": 594,
      "Reference": 40
    }
  ],
  "Objects": [
    {
      "Height": 300,
      "Length": 300,
      "Cost": 90000,
      "Reference": 1
    }
  ],
  "CuttingPatterns": [
    {
      "Object": 1,
      "Root": {
        "Type": "Structure",
        "Orientation": "V",
        "Children": [
          {
            "Type": "Structure",
            "Orientation": "H",
            "Children": [
              {
                "Type": "Structure",
                "Orientation": "V",
                "Children": [
                  {
                    "Type": "Structure",
                    "Orientation": "H",
                    "Children": [
                      {
                        "Type": "Structure",
                        "Orientation": "V",
                        "Children": [
                          {
                            "Type": "Structure",
                            "Orientation": "H",
                            "Children": [
                              {
                                "Type": "Structure",
                                "Orientation": "V",
                                "Children": [
                                  {
                                    "Type": "Item",
                                    "Item": 26,
                                    "Height": 98,
                                    "Length": 76
                                  },
                                  {
                                    "Type": "Structure",
                                    "Orientation": "H",
                                    "Children": [
                                      {
                                        "Type": "Item",
                                        "Item": 32,
                                        "Height": 94,
                                        "Length": 15
                                      },
                                      {
                                        "Type": "Structure",
                                        "Orientation": "V",
                                        "Children": [
                                          {
                                            "Type": "Item",
                                            "Item": 12,
                                            "Height": 3,
                                            "Length": 13
                                          },
                                          {
                                            "Type": "Leftover",
                                            "Height": 3,
                                            "Length": 2
                                          }
                                        ],
                                        "Height": 3,
                                        "Length": 15
                                      },
                                      {
                                        "Type": "Leftover",
                                        "Height": 1,
                                        "Length": 15
                                      }
                                    ],
                                    "Height": 98,
                                    "Length": 15
                                  },
                                  {
                                    "Type": "Structure",
                                    "Orientation": "H",
                                    "Children": [
                                      {
                                        "Type": "Item",
                                        "Item": 30,
                                        "Height": 96,
                                        "Length": 36
                                      },
                                      {
                                        "Type": "Leftover",
                                        "Height": 2,
                                        "Length": 36
                                      }
                                    ],
                                    "Height": 98,
                                    "Length": 36
                                  },
                                  {
                                    "Type": "Structure",
                                    "Orientation": "H",
                                    "Children": [
                                      {
                                        "Type": "Item",
                                        "Item": 25,
                                        "Height": 95,
                                        "Length": 85
                                      },
                                      {
                                        "Type": "Leftover",
                                        "Height": 3,
                                        "Length": 85
                                      }
                                    ],
                                    "Height": 98,
                                    "Length": 85
                                  },
                                  {
                                    "Type": "Leftover",
                                    "Height": 98,
                                    "Length": 1
                                  }
                                ],
                                "Height": 98,
                                "Length": 213
                              },
                              {
                                "Type": "Structure",
                                "Orientation": "V",
                                "Children": [
                                  {
                                    "Type": "Structure",
                                    "Orientation": "H",
                                    "Children": [
                                      {
                                        "Type": "Structure",
                                        "Orientation": "V",
                                        "Children": [
                                          {
                                            "Type": "Item",
                                            "Item": 10,
                                            "Height": 76,
                                            "Length": 49
                                          },
                                          {
                                            "Type": "Structure",
                                            "Orientation": "H",
                                            "Children": [
                                              {
                                                "Type": "Structure",
                                                "Orientation": "V",
                                                "Children": [
                                                  {
                                                    "Type": "Item",
                                                    "Item": 31,
                                                    "Height": 53,
                                                    "Length": 20
                                                  },
                                                  {
                                                    "Type": "Structure",
                                                    "Orientation": "H",
                                                    "Children": [
                                                      {
                                                        "Type": "Item",
                                                        "Item": 27,
                                                        "Height": 41,
                                                        "Length": 1
                                                      },
                                                      {
                                                        "Type": "Leftover",
                                                        "Height": 12,
                                                        "Length": 1
                                                      }
                                                    ],
                                                    "Height": 53,
                                                    "Length": 1
                                                  }
                                                ],
                                                "Height": 53,
                                                "Length": 21
                                              },
                                              {
                                                "Type": "Structure",
                                                "Orientation": "V",
                                                "Children": [
                                                  {
                                                    "Type": "Item",
                                                    "Item": 6,
                                                    "Height": 19,
                                                    "Length": 18
                                                  },
                                                  {
                                                    "Type": "Leftover",
                                                    "Height": 19,
                                                    "Length": 3
                                                  }
                                                ],
                                                "Height": 19,
                                                "Length": 21
                                              },
                                              {
                                                "Type": "Leftover",
                                                "Height": 4,
                                                "Length": 21
                                              }
                                            ],
                                            "Height": 76,
                                            "Length": 21
                                          }
                                        ],
                                        "Height": 76,
                                        "Length": 70
                                      },
                                      {
                                        "Type": "Structure",
                                        "Orientation": "V",
                                        "Children": [
                                          {
                                            "Type": "Item",
                                            "Item": 29,
                                            "Height": 68,
                                            "Length": 42
                                          },
                                          {
                                            "Type": "Leftover",
                                            "Height": 68,
                                            "Length": 28
                                          }
                                        ],
                                        "Height": 68,
                                        "Length": 70
                                      }
                                    ],
                                    "Height": 144,
                                    "Length": 70
                                  },
                                  {
                                    "Type": "Structure",
                                    "Orientation": "H",
                                    "Children": [
                                      {
                                        "Type": "Item",
                                        "Item": 4,
                                        "Height": 100,
                                        "Length": 95
                                      },
                                      {
                                        "Type": "Leftover",
                                        "Height": 44,
                                        "Length": 95
                                      }
                                    ],
                                    "Height": 144,
                                    "Length": 95
                                  },
                                  {
                                    "Type": "Structure",
                                    "Orientation": "H",
                                    "Children": [
                                      {
                                        "Type": "Item",
                                        "Item": 21,
                                        "Height": 99,
                                        "Length": 48
                                      },
                                      {
                                        "Type": "Leftover",
                                        "Height": 45,
                                        "Length": 48
                                      }
                                    ],
                                    "Height": 144,
                                    "Length": 48
                                  }
                                ],
                                "Height": 144,
                                "Length": 213
                              }
                            ],
                            "Height": 242,
                            "Length": 213
                          },
                          {
                            "Type": "Structure",
                            "Orientation": "H",
                            "Children": [
                              {
                                "Type": "Item",
                                "Item": 14,
                                "Height": 77,
                                "Length": 68
                              },
                              {
                                "Type": "Structure",
                                "Orientation": "V",
                                "Children": [
                                  {
                                    "Type": "Structure",
                                    "Orientation": "H",
                                    "Children": [
                                      {
                                        "Type": "Structure",
                                        "Orientation": "V",
                                        "Children": [
                                          {
                                            "Type": "Structure",
                                            "Orientation": "H",
                                            "Children": [
                                              {
                                                "Type": "Item",
                                                "Item": 23,
                                                "Height": 84,
                                                "Length": 15
                                              },
                                              {
                                                "Type": "Leftover",
                                                "Height": 5,
                                                "Length": 15
                                              }
                                            ],
                                            "Height": 89,
                                            "Length": 15
                                          },
                                          {
                                            "Type": "Structure",
                                            "Orientation": "H",
                                            "Children": [
                                              {
                                                "Type": "Item",
                                                "Item": 36,
                                                "Height": 74,
                                                "Length": 24
                                              },
                                              {
                                                "Type": "Leftover",
                                                "Height": 15,
                                                "Length": 24
                                              }
                                            ],
                                            "Height": 89,
                                            "Length": 24
                                          },
                                          {
                                            "Type": "Leftover",
                                            "Height": 89,
                                            "Length": 3
                                          }
                                        ],
                                        "Height": 89,
                                        "Length": 42
                                      },
                                      {
                                        "Type": "Structure",
                                        "Orientation": "V",
                                        "Children": [
                                          {
                                            "Type": "Item",
                                            "Item": 16,
                                            "Height": 76,
                                            "Length": 26
                                          },
                                          {
                                            "Type": "Leftover",
                                            "Height": 76,
                                            "Length": 16
                                          }
                                        ],
                                        "Height": 76,
                                        "Length": 42
                                      }
                                    ],
                                    "Height": 165,
                                    "Length": 42
                                  },
                                  {
                                    "Type": "Structure",
                                    "Orientation": "H",
                                    "Children": [
                                      {
                                        "Type": "Item",
                                        "Item": 22,
                                        "Height": 99,
                                        "Length": 26
                                      },
                                      {
                                        "Type": "Leftover",
                                        "Height": 66,
                                        "Length": 26
                                      }
                                    ],
                                    "Height": 165,
                                    "Length": 26
                                  }
                                ],
                                "Height": 165,
                                "Length": 68
                              }
                            ],
                            "Height": 242,
                            "Length": 68
                          }
                        ],
                        "Height": 242,
                        "Length": 281
                      },
                      {
                        "Type": "Structure",
                        "Orientation": "V",
                        "Children": [
                          {
                            "Type": "Item",
                            "Item": 37,
                            "Height": 34,
                            "Length": 78
                          },
                          {
                            "Type": "Structure",
                            "Orientation": "H",
                            "Children": [
                              {
                                "Type": "Item",
                                "Item": 20,
                                "Height": 26,
                                "Length": 60
                              },
                              {
                                "Type": "Leftover",
                                "Height": 8,
                                "Length": 60
                              }
                            ],
                            "Height": 34,
                            "Length": 60
                          },
                          {
                            "Type": "Leftover",
                            "Height": 34,
                            "Length": 143
                          }
                        ],
                        "Height": 34,
                        "Length": 281
                      }
                    ],
                    "Height": 276,
                    "Length": 281
                  },
                  {
                    "Type": "Structure",
                    "Orientation": "H",
                    "Children": [
                      {
                        "Type": "Item",
                        "Item": 15,
                        "Height": 79,
                        "Length": 19
                      },
                      {
                        "Type": "Item",
                        "Item": 7,
                        "Height": 60,
                        "Length": 19
                      },
                      {
                        "Type": "Structure",
                        "Orientation": "V",
                        "Children": [
                          {
                            "Type": "Item",
                            "Item": 9,
                            "Height": 83,
                            "Length": 12
                          },
                          {
                            "Type": "Leftover",
                            "Height": 83,
                            "Length": 7
                          }
                        ],
                        "Height": 83,
                        "Length": 19
                      },
                      {
                        "Type": "Leftover",
                        "Height": 54,
                        "Length": 19
                      }
                    ],
                    "Height": 276,
                    "Length": 19
                  }
                ],
                "Height": 276,
                "Length": 300
              },
              {
                "Type": "Structure",
                "Orientation": "V",
                "Children": [
                  {
                    "Type": "Item",
                    "Item": 17,
                    "Height": 24,
                    "Length": 11
                  },
                  {
                    "Type": "Structure",
                    "Orientation": "H",
                    "Children": [
                      {
                        "Type": "Item",
                        "Item": 34,
                        "Height": 16,
                        "Length": 96
                      },
                      {
                        "Type": "Leftover",
                        "Height": 8,
                        "Length": 96
                      }
                    ],
                    "Height": 24,
                    "Length": 96
                  },
                  {
                    "Type": "Leftover",
                    "Height": 24,
                    "Length": 193
                  }
                ],
                "Height": 24,
                "Length": 300
              }
            ],
            "Height": 300,
            "Length": 300
          }
        ],
        "Height": 300,
        "Length": 300
      }
    },
    {
      "Object": 1,
      "Root": {
        "Type": "Structure",
        "Orientation": "H",
        "Children": [
          {
            "Type": "Structure",
            "Orientation": "V",
            "Children": [
              {
                "Type": "Item",
                "Item": 1,
                "Height": 95,
                "Length": 77
              },
              {
                "Type": "Structure",
                "Orientation": "H",
                "Children": [
                  {
                    "Type": "Item",
                    "Item": 5,
                    "Height": 73,
                    "Length": 73
                  },
                  {
                    "Type": "Structure",
                    "Orientation": "V",
                    "Children": [
                      {
                        "Type": "Item",
                        "Item": 40,
                        "Height": 9,
                        "Length": 66
                      },
                      {
                        "Type": "Leftover",
                        "Height": 9,
                        "Length": 7
                      }
                    ],
                    "Height": 9,
                    "Length": 73
                  },
                  {
                    "Type": "Structure",
                    "Orientation": "V",
                    "Children": [
                      {
                        "Type": "Structure",
                        "Orientation": "H",
                        "Children": [
                          {
                            "Type": "Item",
                            "Item": 18,
                            "Height": 11,
                            "Length": 31
                          },
                          {
                            "Type": "Leftover",
                            "Height": 2,
                            "Length": 31
                          }
                        ],
                        "Height": 13,
                        "Length": 31
                      },
                      {
                        "Type": "Structure",
                        "Orientation": "H",
                        "Children": [
                          {
                            "Type": "Item",
                            "Item": 3,
                            "Height": 11,
                            "Length": 30
                          },
                          {
                            "Type": "Leftover",
                            "Height": 2,
                            "Length": 30
                          }
                        ],
                        "Height": 13,
                        "Length": 30
                      },
                      {
                        "Type": "Leftover",
                        "Height": 13,
                        "Length": 12
                      }
                    ],
                    "Height": 13,
                    "Length": 73
                  }
                ],
                "Height": 95,
                "Length": 73
              },
              {
                "Type": "Structure",
                "Orientation": "H",
                "Children": [
                  {
                    "Type": "Item",
                    "Item": 35,
                    "Height": 75,
                    "Length": 93
                  },
                  {
                    "Type": "Structure",
                    "Orientation": "V",
                    "Children": [
                      {
                        "Type": "Item",
                        "Item": 38,
                        "Height": 12,
                        "Length": 77
                      },
                      {
                        "Type": "Leftover",
                        "Height": 12,
                        "Length": 16
                      }
                    ],
                    "Height": 12,
                    "Length": 93
                  },
                  {
                    "Type": "Leftover",
                    "Height": 8,
                    "Length": 93
                  }
                ],
                "Height": 95,
                "Length": 93
              },
              {
                "Type": "Structure",
                "Orientation": "H",
                "Children": [
                  {
                    "Type": "Structure",
                    "Orientation": "V",
                    "Children": [
                      {
                        "Type": "Item",
                        "Item": 2,
                        "Height": 50,
                        "Length": 53
                      },
                      {
                        "Type": "Leftover",
                        "Height": 50,
                        "Length": 4
                      }
                    ],
                    "Height": 50,
                    "Length": 57
                  },
                  {
                    "Type": "Leftover",
                    "Height": 45,
                    "Length": 57
                  }
                ],
                "Height": 95,
                "Length": 57
              }
            ],
            "Height": 95,
            "Length": 300
          },
          {
            "Type": "Structure",
            "Orientation": "V",
            "Children": [
              {
                "Type": "Item",
                "Item": 19,
                "Height": 60,
                "Length": 73
              },
              {
                "Type": "Structure",
                "Orientation": "H",
                "Children": [
                  {
                    "Type": "Structure",
                    "Orientation": "V",
                    "Children": [
                      {
                        "Type": "Item",
                        "Item": 13,
                        "Height": 48,
                        "Length": 84
                      },
                      {
                        "Type": "Structure",
                        "Orientation": "H",
                        "Children": [
                          {
                            "Type": "Item",
                            "Item": 28,
                            "Height": 46,
                            "Length": 49
                          },
                          {
                            "Type": "Leftover",
                            "Height": 2,
                            "Length": 49
                          }
                        ],
                        "Height": 48,
                        "Length": 49
                      },
                      {
                        "Type": "Leftover",
                        "Height": 48,
                        "Length": 94
                      }
                    ],
                    "Height": 48,
                    "Length": 227
                  },
                  {
                    "Type": "Leftover",
                    "Height": 12,
                    "Length": 227
                  }
                ],
                "Height": 60,
                "Length": 227
              }
            ],
            "Height": 60,
            "Length": 300
          },
          {
            "Type": "Structure",
            "Orientation": "V",
            "Children": [
              {
                "Type": "Structure",
                "Orientation": "H",
                "Children": [
                  {
                    "Type": "Item",
                    "Item": 39,
                    "Height": 96,
                    "Length": 77
                  },
                  {
                    "Type": "Item",
                    "Item": 33,
                    "Height": 7,
                    "Length": 77
                  },
                  {
                    "Type": "Structure",
                    "Orientation": "V",
                    "Children": [
                      {
                        "Type": "Item",
                        "Item": 24,
                        "Height": 42,
                        "Length": 72
                      },
                      {
                        "Type": "Leftover",
                        "Height": 42,
                        "Length": 5
                      }
                    ],
                    "Height": 42,
                    "Length": 77
                  }
                ],
                "Height": 145,
                "Length": 77
              },
              {
                "Type": "Structure",
                "Orientation": "H",
                "Children": [
                  {
                    "Type": "Item",
                    "Item": 8,
                    "Height": 52,
                    "Length": 99
                  },
                  {
                    "Type": "Structure",
                    "Orientation": "V",
                    "Children": [
                      {
                        "Type": "Structure",
                        "Orientation": "H",
                        "Children": [
                          {
                            "Type": "Item",
                            "Item": 11,
                            "Height": 87,
                            "Length": 30
                          },
                          {
                            "Type": "Leftover",
                            "Height": 6,
                            "Length": 30
                          }
                        ],
                        "Height": 93,
                        "Length": 30
                      },
                      {
                        "Type": "Leftover",
                        "Height": 93,
                        "Length": 69
                      }
                    ],
                    "Height": 93,
                    "Length": 99
                  }
                ],
                "Height": 145,
                "Length": 99
              },
              {
                "Type": "Leftover",
                "Height": 145,
                "Length": 124
              }
            ],
            "Height": 145,
            "Length": 300
          }
        ],
        "Height": 300,
        "Length": 300
      }
    }
  ]
}