{
  "Name": "MB_C7_38",
  "Items": [
    {
      "Height": 76,
      "Length": 28,
      "Demand": 1,
      "Value": 2128,
      "Reference": 1
    },
    {
      "Height": 90,
      "Length": 20,
      "Demand": 1,
      "Value": 1800,
      "Reference": 2
    },
    {
      "Height": 100,
      "Length": 1,
      "Demand": 1,
      "Value": 100,
      "Reference": 3
    },
    {
      "Height": 77,
      "Length": 63,
      "Demand": 1,
      "Value": 4851,
      "Reference": 4
    },
    {
      "Height": 12,
      "Length": 27,
      "Demand": 1,
      "Value": 324,
      "Reference": 5
    },
    {
      "Height": 22,
      "Length": 89,
      "Demand": 1,
      "Value": 1958,
      "Reference": 6
    },
    {
      "Height": 66,
      "Length": 6,
      "Demand": 1,
      "Value": 396,
      "Reference": 7
    },
    {
      "Height": 79,
      "Length": 34,
      "Demand": 1,
      "Value": 2686,
      "Reference": 8
    },
    {
      "Height": 78,
      "Length": 37,
      "Demand": 1,
      "Value": 2886,
      "Reference": 9
    },
    {
      "Height": 79,
      "Length": 11,
      "Demand": 1,
      "Value": 869,
      "Reference": 10
    },
    {
      "Height": 75,
      "Length": 22,
      "Demand": 1,
      "Value": 1650,
      "Reference": 11
    },
    {
      "Height": 23,
      "Length": 76,
      "Demand": 1,
      "Value": 1748,
      "Reference": 12
    },
    {
      "Height": 92,
      "Length": 10,
      "Demand": 1,
      "Value": 920,
      "Reference": 13
    },
    {
      "Height": 79,
      "Length": 98,
      "Demand": 1,
      "Value": 7742,
      "Reference": 14
    },
    {
      "Height": 89,
      "Length": 100,
      "Demand": 1,
      "Value": 8900,
      "Reference": 15
    },
    {
      "Height": 38,
      "Length": 9,
      "Demand": 1,
      "Value": 342,
      "Reference": 16
    },
    {
      "Height": 19,
      "Length": 44,
      "Demand": 1,
      "Value": 836,
      "Reference": 17
    },
    {
      "Height": 100,
      "Length": 48,
      "Demand": 1,
      "Value": 4800,
      "Reference": 18
    },
    {
      "Height": 83,
      "Length": 40,
      "Demand": 1,
      "Value": 3320,
      "Reference": 19
    },
    {
      "Height": 76,
      "Length": 14,
      "Demand": 1,
      "Value": 1064,
      "Reference": 20
    },
    {
      "Height": 11,
      "Length": 93,
      "Demand": 1,
      "Value": 1023,
      "Reference": 21
    },
    {
      "Height": 83,
      "Length": 58,
      "Demand": 1,
      "Value": 4814,
      "Reference": 22
    },
    {
      "Height": 82,
      "Length": 41,
      "Demand": 1,
      "Value": 3362,
      "Reference": 23
    },
    {
      "Height": 68,
      "Length": 31,
      "Demand": 1,
      "Value": 2108,
      "Reference": 24
    },
    {
      "Height": 65,
      "Length": 96,
      "Demand": 1,
      "Value": 6240,
      "Reference": 25
    },
    {
      "Height": 84,
      "Length": 31,
      "Demand": 1,
      "Value": 2604,
      "Reference": 26
    },
    {
      "Height": 89,
      "Length": 5,
      "Demand": 1,
      "Value": 445,
      "Reference": 27
    },
    {
      "Height": 68,
      "Length": 10,
      "Demand": 1,
      "Value": 680,
      "Reference": 28
    },
    {
      "Height": 87,
      "Length": 15,
      "Demand": 1,
      "Value": 1305,
      "Reference": 29
    },
    {
      "Height": 34,
      "Length": 76,
      "Demand": 1,
      "Value": 2584,
      "Reference": 30
    },
    {
      "Height": 69,
      "Length": 29,
      "Demand": 1,
      "Value": 2001,
      "Reference": 31
    },
    {
      "Height": 76,
      "Length": 50,
      "Demand": 1,
      "Value": 3800,
      "Reference": 32
    },
    {
      "Height": 71,
      "Length": 46,
      "Demand": 1,
      "Value": 3266,
      "Reference": 33
    },
    {
      "Height": 66,
      "Length": 12,
      "Demand": 1,
      "Value": 792,
      "Reference": 34
    },
    {
      "Height": 92,
      "Length": 16,
      "Demand": 1,
      "Value": 1472,
      "Reference": 35
    },
    {
      "Height": 90,
      "Length": 51,
      "Demand": 1,
      "Value": 4590,
      "Reference": 36
    },
    {
      "Height": 98,
      "Length": 38,
      "Demand": 1,
      "Value": 3724,
      "Reference": 37
    },
    {
      "Height": 87,
      "Length": 20,
      "Demand": 1,
      "Value": 1740,
      "Reference": 38
    },
    {
      "Height": 89,
      "Length": 14,
      "Demand": 1,
      "Value": 1246,
      "Reference": 39
    },
    {
      "Height": 83,
      "Length": 15,
      "Demand": 1,
      "Value": 1245,
      "Reference": 40
    },
    {
      "Height": 99,
      "Length": 42,
      "Demand": 1,
      "Value": 4158,
      "Reference": 41
    },
    {
      "Height": 81,
      "Length": 39,
      "Demand": 1,
      "Value": 3159,
      "Reference": 42
    },
    {
      "Height": 94,
      "Length": 24,
      "Demand": 1,
      "Value": 2256,
      "Reference": 43
    },
    {
      "Height": 81,
      "Length": 40,
      "Demand": 1,
      "Value": 3240,
      "Reference": 44
    },
    {
      "Height": 73,
      "Length": 8,
      "Demand": 1,
      "Value": 584,
      "Reference": 45
    },
    {
      "Height": 83,
      "Length": 20,
      "Demand": 1,
      "Value": 1660,
      "Reference": 46
    },
    {
      "Height": 9,
      "Length": 45,
      "Demand": 1,
      "Value": 405,
      "Reference": 47
    },
    {
      "Height": 87,
      "Length": 27,
      "Demand": 1,
      "Value": 2349,
      "Reference": 48
    },
    {
      "Height": 35,
      "Length": 35,
      "Demand": 1,
      "Value": 1225,
      "Reference": 49
    },
    {
      "Height": 93,
      "Length": 13,
      "Demand": 1,
      "Value": 1209,
      "Reference": 50
    },
    {
      "Height": 92,
      "Length": 28,
      "Demand": 1,
      "Value": 2576,
      "Reference": 51
    },
    {
      "Height": 50,
      "Length": 75,
      "Demand": 1,
      "Value": 3750,
      "Reference": 52
    },
    {
      "Height": 80,
      "Length": 24,
      "Demand": 1,
      "Value": 1920,
      "Reference": 53
    },
    {
      "Height": 76,
      "Length": 17,
      "Demand": 1,
      "Value": 1292,
      "Reference": 54
    },
    {
      "Height": 86,
      "Length": 23,
      "Demand": 1,
      "Value": 1978,
      "Reference": 55
    },
    {
      "Height": 88,
      "Length": 36,
      "Demand": 1,
      "Value": 3168,
      "Reference": 56
    },
    {
      "Height": 78,
      "Length": 25,
      "Demand": 1,
      "Value": 1950,
      "Reference": 57
    },
    {
      "Height": 53,
      "Length": 83,
      "Demand": 1,
      "Value": 4399,
      "Reference": 58
    },
    {
      "Height": 89,
      "Length": 29,
      "Demand": 1,
      "Value": 2581,
      "Reference": 59
    },
    {
      "Height": 84,
      "Length": 8,
      "Demand": 1,
      "Value": 672,
      "Reference": 60
    },
    {
      "Height": 84,
      "Length": 37,
      "Demand": 1,
      "Value": 3108,
      "Reference": 61
    },
    {
      "Height": 52,
      "Length": 60,
      "Demand": 1,
      "Value": 3120,
      "Reference": 62
    },
    {
      "Height": 99,
      "Length": 48,
      "Demand": 1,
      "Value": 4752,
      "Reference": 63
    },
    {
      "Height": 88,
      "Length": 41,
      "Demand": 1,
      "Value": 3608,
      "Reference": 64
    },
    {
      "Height": 99,
      "Length": 11,
      "Demand": 1,
      "Value": 1089,
      "Reference": 65
    },
    {
      "Height": 75,
      "Length": 50,
      "Demand": 1,
      "Value": 3750,
      "Reference": 66
    },
    {
      "Height": 83,
      "Length": 27,
      "Demand": 1,
      "Value": 2241,
      "Reference": 67
    },
    {
      "Height": 100,
      "Length": 37,
      "Demand": 1,
      "Value": 3700,
      "Reference": 68
    },
    {
      "Height": 86,
      "Length": 47,
      "Demand": 1,
      "Value": 4042,
      "Reference": 69
    },
    {
      "Height": 91,
      "Length": 1,
      "Demand": 1,
      "Value": 91,
      "Reference": 70
    },
    {
      "Height": 62,
      "Length": 68,
      "Demand": 1,
      "Value": 4216,
      "Reference": 71
    },
    {
      "Height": 85,
      "Length": 43,
      "Demand": 1,
      "Value": 3655,
      "Reference": 72
    },
    {
      "Height": 82,
      "Length": 44,
      "Demand": 1,
      "Value": 3608,
      "Reference": 73
    },
    {
      "Height": 80,
      "Length": 14,
      "Demand": 1,
      "Value": 1120,
      "Reference": 74
    },
    {
      "Height": 13,
      "Length": 80,
      "Demand": 1,
      "Value": 1040,
      "Reference": 75
    },
    {
      "Height": 18,
      "Length": 12,
      "Demand": 1,
      "Value": 216,
      "Reference": 76
    },
    {
      "Height": 86,
      "Length": 3,
      "Demand": 1,
      "Value": 258,
      "Reference": 77
    },
    {
      "Height": 18,
      "Length": 38,
      "Demand": 1,
      "Value": 684,
      "Reference": 78
    },
    {
      "Height": 25,
      "Length": 37,
      "Demand": 1,
      "Value": 925,
      "Reference": 79
    },
    {
      "Height": 20,
      "Length": 42,
      "Demand": 1,
      "Value": 840,
      "Reference": 80
    }
  ],
  "Objects": [
    {
      "Height": 100,
      "Length": 100,
      "Cost": 10000,
      "Reference": 1
    },
    {
      "Height": 71,
      "Length": 89,
      "Cost": 6319,
      "Reference": 2
    },
    {
      "Height": 56,
      "Length": 56,
      "Cost": 3136,
      "Reference": 3
    },
    {
      "Height": 98,
      "Length": 75,
      "Cost": 7350,
      "Reference": 4
    },
    {
      "Height": 90,
      "Length": 99,
      "Cost": 8910,
      "Reference": 5
    }
  ],
  "CuttingPatterns": [
    {
      "Object": 2,
      "Root": {
        "Type": "Structure",
        "Orientation": "V",
        "Children": [
          {
            "Type": "Item",
            "Item": 33,
            "Height": 71,
            "Length": 46
          },
          {
            "Type": "Structure",
            "Orientation": "H",
            "Children": [
              {
                "Type": "Item",
                "Item": 24,
                "Height": 68,
                "Length": 31
              },
              {
                "Type": "Leftover",
                "Height": 3,
                "Length": 31
              }
            ],
            "Height": 71,
            "Length": 31
          },
          {
            "Type": "Structure",
            "Orientation": "H",
            "Children": [
              {
                "Type": "Item",
                "Item": 34,
                "Height": 66,
                "Length": 12
              },
              {
                "Type": "Leftover",
                "Height": 5,
                "Length": 12
              }
            ],
            "Height": 71,
            "Length": 12
          }
        ],
        "Height": 71,
        "Length": 89
      }
    },
    {
      "Object": 2,
      "Root": {
        "Type": "Structure",
        "Orientation": "H",
        "Children": [
          {
            "Type": "Structure",
            "Orientation": "V",
            "Children": [
              {
                "Type": "Structure",
                "Orientation": "H",
                "Children": [
                  {
                    "Type": "Item",
                    "Item": 31,
                    "Height": 69,
                    "Length": 29
                  },
                  {
                    "Type": "Leftover",
                    "Height": 2,
                    "Length": 29
                  }
                ],
                "Height": 71,
                "Length": 29
              },
              {
                "Type": "Structure",
                "Orientation": "H",
                "Children": [
                  {
                    "Type": "Item",
                    "Item": 62,
                    "Height": 52,
                    "Length": 60
                  },
                  {
                    "Type": "Structure",
                    "Orientation": "V",
                    "Children": [
                      {
                        "Type": "Item",
                        "Item": 17,
                        "Height": 19,
                        "Length": 44
                      },
                      {
                        "Type": "Leftover",
                        "Height": 19,
                        "Length": 16
                      }
                    ],
                    "Height": 19,
                    "Length": 60
                  }
                ],
                "Height": 71,
                "Length": 60
              }
            ],
            "Height": 71,
            "Length": 89
          }
        ],
        "Height": 71,
        "Length": 89
      }
    },
    {
      "Object": 5,
      "Root": {
        "Type": "Structure",
        "Orientation": "H",
        "Children": [
          {
            "Type": "Structure",
            "Orientation": "V",
            "Children": [
              {
                "Type": "Item",
                "Item": 44,
                "Height": 81,
                "Length": 40
              },
              {
                "Type": "Structure",
                "Orientation": "H",
                "Children": [
                  {
                    "Type": "Item",
                    "Item": 8,
                    "Height": 79,
                    "Length": 34
                  },
                  {
                    "Type": "Leftover",
                    "Height": 2,
                    "Length": 34
                  }
                ],
                "Height": 81,
                "Length": 34
              },
              {
                "Type": "Structure",
                "Orientation": "H",
                "Children": [
                  {
                    "Type": "Item",
                    "Item": 57,
                    "Height": 78,
                    "Length": 25
                  },
                  {
                    "Type": "Leftover",
                    "Height": 3,
                    "Length": 25
                  }
                ],
                "Height": 81,
                "Length": 25
              }
            ],
            "Height": 81,
            "Length": 99
          },
          {
            "Type": "Structure",
            "Orientation": "V",
            "Children": [
              {
                "Type": "Item",
                "Item": 47,
                "Height": 9,
                "Length": 45
              },
              {
                "Type": "Leftover",
                "Height": 9,
                "Length": 54
              }
            ],
            "Height": 9,
            "Length": 99
          }
        ],
        "Height": 90,
        "Length": 99
      }
    },
    {
      "Object": 5,
      "Root": {
        "Type": "Structure",
        "Orientation": "V",
        "Children": [
          {
            "Type": "Structure",
            "Orientation": "H",
            "Children": [
              {
                "Type": "Item",
                "Item": 55,
                "Height": 86,
                "Length": 23
              },
              {
                "Type": "Leftover",
                "Height": 4,
                "Length": 23
              }
            ],
            "Height": 90,
            "Length": 23
          },
          {
            "Type": "Structure",
            "Orientation": "H",
            "Children": [
              {
                "Type": "Item",
                "Item": 30,
                "Height": 34,
                "Length": 76
              },
              {
                "Type": "Structure",
                "Orientation": "V",
                "Children": [
                  {
                    "Type": "Item",
                    "Item": 52,
                    "Height": 50,
                    "Length": 75
                  },
                  {
                    "Type": "Leftover",
                    "Height": 50,
                    "Length": 1
                  }
                ],
                "Height": 50,
                "Length": 76
              },
              {
                "Type": "Leftover",
                "Height": 6,
                "Length": 76
              }
            ],
            "Height": 90,
            "Length": 76
          }
        ],
        "Height": 90,
        "Length": 99
      }
    },
    {
      "Object": 5,
      "Root": {
        "Type": "Structure",
        "Orientation": "H",
        "Children": [
          {
            "Type": "Structure",
            "Orientation": "V",
            "Children": [
              {
                "Type": "Item",
                "Item": 36,
                "Height": 90,
                "Length": 51
              },
              {
                "Type": "Structure",
                "Orientation": "H",
                "Children": [
                  {
                    "Type": "Item",
                    "Item": 26,
                    "Height": 84,
                    "Length": 31
                  },
                  {
                    "Type": "Leftover",
                    "Height": 6,
                    "Length": 31
                  }
                ],
                "Height": 90,
                "Length": 31
              },
              {
                "Type": "Structure",
                "Orientation": "H",
                "Children": [
                  {
                    "Type": "Item",
                    "Item": 54,
                    "Height": 76,
                    "Length": 17
                  },
                  {
                    "Type": "Leftover",
                    "Height": 14,
                    "Length": 17
                  }
                ],
                "Height": 90,
                "Length": 17
              }
            ],
            "Height": 90,
            "Length": 99
          }
        ],
        "Height": 90,
        "Length": 99
      }
    },
    {
      "Object": 1,
      "Root": {
        "Type": "Structure",
        "Orientation": "V",
        "Children": [
          {
            "Type": "Structure",
            "Orientation": "H",
            "Children": [
              {
                "Type": "Item",
                "Item": 65,
                "Height": 99,
                "Length": 11
              },
              {
                "Type": "Leftover",
                "Height": 1,
                "Length": 11
              }
            ],
            "Height": 100,
            "Length": 11
          },
          {
            "Type": "Structure",
            "Orientation": "H",
            "Children": [
              {
                "Type": "Item",
                "Item": 35,
                "Height": 92,
                "Length": 16
              },
              {
                "Type": "Leftover",
                "Height": 8,
                "Length": 16
              }
            ],
            "Height": 100,
            "Length": 16
          },
          {
            "Type": "Structure",
            "Orientation": "H",
            "Children": [
              {
                "Type": "Item",
                "Item": 27,
                "Height": 89,
                "Length": 5
              },
              {
                "Type": "Leftover",
                "Height": 11,
                "Length": 5
              }
            ],
            "Height": 100,
            "Length": 5
          },
          {
            "Type": "Structure",
            "Orientation": "H",
            "Children": [
              {
                "Type": "Item",
                "Item": 71,
                "Height": 62,
                "Length": 68
              },
              {
                "Type": "Structure",
                "Orientation": "V",
                "Children": [
                  {
                    "Type": "Item",
                    "Item": 16,
                    "Height": 38,
                    "Length": 9
                  },
                  {
                    "Type": "Structure",
                    "Orientation": "H",
                    "Children": [
                      {
                        "Type": "Item",
                        "Item": 49,
                        "Height": 35,
                        "Length": 35
                      },
                      {
                        "Type": "Leftover",
                        "Height": 3,
                        "Length": 35
                      }
                    ],
                    "Height": 38,
                    "Length": 35
                  },
                  {
                    "Type": "Leftover",
                    "Height": 38,
                    "Length": 24
                  }
                ],
                "Height": 38,
                "Length": 68
              }
            ],
            "Height": 100,
            "Length": 68
          }
        ],
        "Height": 100,
        "Length": 100
      }
    },
    {
      "Object": 5,
      "Root": {
        "Type": "Structure",
        "Orientation": "V",
        "Children": [
          {
            "Type": "Structure",
            "Orientation": "H",
            "Children": [
              {
                "Type": "Item",
                "Item": 77,
                "Height": 86,
                "Length": 3
              },
              {
                "Type": "Leftover",
                "Height": 4,
                "Length": 3
              }
            ],
            "Height": 90,
            "Length": 3
          },
          {
            "Type": "Structure",
            "Orientation": "H",
            "Children": [
              {
                "Type": "Item",
                "Item": 25,
                "Height": 65,
                "Length": 96
              },
              {
                "Type": "Structure",
                "Orientation": "V",
                "Children": [
                  {
                    "Type": "Structure",
                    "Orientation": "H",
                    "Children": [
                      {
                        "Type": "Item",
                        "Item": 12,
                        "Height": 23,
                        "Length": 76
                      },
                      {
                        "Type": "Leftover",
                        "Height": 2,
                        "Length": 76
                      }
                    ],
                    "Height": 25,
                    "Length": 76
                  },
                  {
                    "Type": "Leftover",
                    "Height": 25,
                    "Length": 20
                  }
                ],
                "Height": 25,
                "Length": 96
              }
            ],
            "Height": 90,
            "Length": 96
          }
        ],
        "Height": 90,
        "Length": 99
      }
    },
    {
      "Object": 5,
      "Root": {
        "Type": "Structure",
        "Orientation": "V",
        "Children": [
          {
            "Type": "Structure",
            "Orientation": "H",
            "Children": [
              {
                "Type": "Item",
                "Item": 56,
                "Height": 88,
                "Length": 36
              },
              {
                "Type": "Leftover",
                "Height": 2,
                "Length": 36
              }
            ],
            "Height": 90,
            "Length": 36
          },
          {
            "Type": "Structure",
            "Orientation": "H",
            "Children": [
              {
                "Type": "Item",
                "Item": 38,
                "Height": 87,
                "Length": 20
              },
              {
                "Type": "Leftover",
                "Height": 3,
                "Length": 20
              }
            ],
            "Height": 90,
            "Length": 20
          },
          {
            "Type": "Structure",
            "Orientation": "H",
            "Children": [
              {
                "Type": "Item",
                "Item": 53,
                "Height": 80,
                "Length": 24
              },
              {
                "Type": "Leftover",
                "Height": 10,
                "Length": 24
              }
            ],
            "Height": 90,
            "Length": 24
          },
          {
            "Type": "Structure",
            "Orientation": "H",
            "Children": [
              {
                "Type": "Item",
                "Item": 10,
                "Height": 79,
                "Length": 11
              },
              {
                "Type": "Leftover",
                "Height": 11,
                "Length": 11
              }
            ],
            "Height": 90,
            "Length": 11
          },
          {
            "Type": "Structure",
            "Orientation": "H",
            "Children": [
              {
                "Type": "Item",
                "Item": 45,
                "Height": 73,
                "Length": 8
              },
              {
                "Type": "Leftover",
                "Height": 17,
                "Length": 8
              }
            ],
            "Height": 90,
            "Length": 8
          }
        ],
        "Height": 90,
        "Length": 99
      }
    },
    {
      "Object": 5,
      "Root": {
        "Type": "Structure",
        "Orientation": "V",
        "Children": [
          {
            "Type": "Structure",
            "Orientation": "H",
            "Children": [
              {
                "Type": "Item",
                "Item": 59,
                "Height": 89,
                "Length": 29
              },
              {
                "Type": "Leftover",
                "Height": 1,
                "Length": 29
              }
            ],
            "Height": 90,
            "Length": 29
          },
          {
            "Type": "Structure",
            "Orientation": "H",
            "Children": [
              {
                "Type": "Item",
                "Item": 48,
                "Height": 87,
                "Length": 27
              },
              {
                "Type": "Leftover",
                "Height": 3,
                "Length": 27
              }
            ],
            "Height": 90,
            "Length": 27
          },
          {
            "Type": "Structure",
            "Orientation": "H",
            "Children": [
              {
                "Type": "Item",
                "Item": 72,
                "Height": 85,
                "Length": 43
              },
              {
                "Type": "Leftover",
                "Height": 5,
                "Length": 43
              }
            ],
            "Height": 90,
            "Length": 43
          }
        ],
        "Height": 90,
        "Length": 99
      }
    },
    {
      "Object": 1,
      "Root": {
        "Type": "Structure",
        "Orientation": "V",
        "Children": [
          {
            "Type": "Structure",
            "Orientation": "H",
            "Children": [
              {
                "Type": "Structure",
                "Orientation": "V",
                "Children": [
                  {
                    "Type": "Structure",
                    "Orientation": "H",
                    "Children": [
                      {
                        "Type": "Item",
                        "Item": 32,
                        "Height": 76,
                        "Length": 50
                      },
                      {
                        "Type": "Leftover",
                        "Height": 2,
                        "Length": 50
                      }
                    ],
                    "Height": 78,
                    "Length": 50
                  },
                  {
                    "Type": "Structure",
                    "Orientation": "H",
                    "Children": [
                      {
                        "Type": "Item",
                        "Item": 1,
                        "Height": 76,
                        "Length": 28
                      },
                      {
                        "Type": "Leftover",
                        "Height": 2,
                        "Length": 28
                      }
                    ],
                    "Height": 78,
                    "Length": 28
                  },
                  {
                    "Type": "Structure",
                    "Orientation": "H",
                    "Children": [
                      {
                        "Type": "Item",
                        "Item": 11,
                        "Height": 75,
                        "Length": 22
                      },
                      {
                        "Type": "Leftover",
                        "Height": 3,
                        "Length": 22
                      }
                    ],
                    "Height": 78,
                    "Length": 22
                  }
                ],
                "Height": 78,
                "Length": 100
              },
              {
                "Type": "Structure",
                "Orientation": "V",
                "Children": [
                  {
                    "Type": "Item",
                    "Item": 6,
                    "Height": 22,
                    "Length": 89
                  },
                  {
                    "Type": "Leftover",
                    "Height": 22,
                    "Length": 11
                  }
                ],
                "Height": 22,
                "Length": 100
              }
            ],
            "Height": 100,
            "Length": 100
          }
        ],
        "Height": 100,
        "Length": 100
      }
    },
    {
      "Object": 5,
      "Root": {
        "Type": "Structure",
        "Orientation": "V",
        "Children": [
          {
            "Type": "Structure",
            "Orientation": "H",
            "Children": [
              {
                "Type": "Structure",
                "Orientation": "V",
                "Children": [
                  {
                    "Type": "Item",
                    "Item": 22,
                    "Height": 83,
                    "Length": 58
                  },
                  {
                    "Type": "Structure",
                    "Orientation": "H",
                    "Children": [
                      {
                        "Type": "Item",
                        "Item": 23,
                        "Height": 82,
                        "Length": 41
                      },
                      {
                        "Type": "Leftover",
                        "Height": 1,
                        "Length": 41
                      }
                    ],
                    "Height": 83,
                    "Length": 41
                  }
                ],
                "Height": 83,
                "Length": 99
              },
              {
                "Type": "Leftover",
                "Height": 7,
                "Length": 99
              }
            ],
            "Height": 90,
            "Length": 99
          }
        ],
        "Height": 90,
        "Length": 99
      }
    },
    {
      "Object": 1,
      "Root": {
        "Type": "Structure",
        "Orientation": "V",
        "Children": [
          {
            "Type": "Structure",
            "Orientation": "H",
            "Children": [
              {
                "Type": "Item",
                "Item": 63,
                "Height": 99,
                "Length": 48
              },
              {
                "Type": "Leftover",
                "Height": 1,
                "Length": 48
              }
            ],
            "Height": 100,
            "Length": 48
          },
          {
            "Type": "Structure",
            "Orientation": "H",
            "Children": [
              {
                "Type": "Item",
                "Item": 37,
                "Height": 98,
                "Length": 38
              },
              {
                "Type": "Leftover",
                "Height": 2,
                "Length": 38
              }
            ],
            "Height": 100,
            "Length": 38
          },
          {
            "Type": "Structure",
            "Orientation": "H",
            "Children": [
              {
                "Type": "Item",
                "Item": 74,
                "Height": 80,
                "Length": 14
              },
              {
                "Type": "Structure",
                "Orientation": "V",
                "Children": [
                  {
                    "Type": "Structure",
                    "Orientation": "H",
                    "Children": [
                      {
                        "Type": "Item",
                        "Item": 76,
                        "Height": 18,
                        "Length": 12
                      },
                      {
                        "Type": "Leftover",
                        "Height": 2,
                        "Length": 12
                      }
                    ],
                    "Height": 20,
                    "Length": 12
                  },
                  {
                    "Type": "Leftover",
                    "Height": 20,
                    "Length": 2
                  }
                ],
                "Height": 20,
                "Length": 14
              }
            ],
            "Height": 100,
            "Length": 14
          }
        ],
        "Height": 100,
        "Length": 100
      }
    },
    {
      "Object": 2,
      "Root": {
        "Type": "Structure",
        "Orientation": "H",
        "Children": [
          {
            "Type": "Structure",
            "Orientation": "V",
            "Children": [
              {
                "Type": "Structure",
                "Orientation": "H",
                "Children": [
                  {
                    "Type": "Item",
                    "Item": 7,
                    "Height": 66,
                    "Length": 6
                  },
                  {
                    "Type": "Leftover",
                    "Height": 5,
                    "Length": 6
                  }
                ],
                "Height": 71,
                "Length": 6
              },
              {
                "Type": "Structure",
                "Orientation": "H",
                "Children": [
                  {
                    "Type": "Item",
                    "Item": 58,
                    "Height": 53,
                    "Length": 83
                  },
                  {
                    "Type": "Structure",
                    "Orientation": "V",
                    "Children": [
                      {
                        "Type": "Item",
                        "Item": 75,
                        "Height": 13,
                        "Length": 80
                      },
                      {
                        "Type": "Leftover",
                        "Height": 13,
                        "Length": 3
                      }
                    ],
                    "Height": 13,
                    "Length": 83
                  },
                  {
                    "Type": "Leftover",
                    "Height": 5,
                    "Length": 83
                  }
                ],
                "Height": 71,
                "Length": 83
              }
            ],
            "Height": 71,
            "Length": 89
          }
        ],
        "Height": 71,
        "Length": 89
      }
    },
    {
      "Object": 1,
      "Root": {
        "Type": "Structure",
        "Orientation": "V",
        "Children": [
          {
            "Type": "Item",
            "Item": 68,
            "Height": 100,
            "Length": 37
          },
          {
            "Type": "Structure",
            "Orientation": "H",
            "Children": [
              {
                "Type": "Item",
                "Item": 66,
                "Height": 75,
                "Length": 50
              },
              {
                "Type": "Structure",
                "Orientation": "V",
                "Children": [
                  {
                    "Type": "Item",
                    "Item": 79,
                    "Height": 25,
                    "Length": 37
                  },
                  {
                    "Type": "Leftover",
                    "Height": 25,
                    "Length": 13
                  }
                ],
                "Height": 25,
                "Length": 50
              }
            ],
            "Height": 100,
            "Length": 50
          },
          {
            "Type": "Structure",
            "Orientation": "H",
            "Children": [
              {
                "Type": "Item",
                "Item": 50,
                "Height": 93,
                "Length": 13
              },
              {
                "Type": "Leftover",
                "Height": 7,
                "Length": 13
              }
            ],
            "Height": 100,
            "Length": 13
          }
        ],
        "Height": 100,
        "Length": 100
      }
    },
    {
      "Object": 1,
      "Root": {
        "Type": "Structure",
        "Orientation": "V",
        "Children": [
          {
            "Type": "Item",
            "Item": 3,
            "Height": 100,
            "Length": 1
          },
          {
            "Type": "Structure",
            "Orientation": "H",
            "Children": [
              {
                "Type": "Item",
                "Item": 14,
                "Height": 79,
                "Length": 98
              },
              {
                "Type": "Structure",
                "Orientation": "V",
                "Children": [
                  {
                    "Type": "Structure",
                    "Orientation": "H",
                    "Children": [
                      {
                        "Type": "Item",
                        "Item": 78,
                        "Height": 18,
                        "Length": 38
                      },
                      {
                        "Type": "Leftover",
                        "Height": 3,
                        "Length": 38
                      }
                    ],
                    "Height": 21,
                    "Length": 38
                  },
                  {
                    "Type": "Leftover",
                    "Height": 21,
                    "Length": 60
                  }
                ],
                "Height": 21,
                "Length": 98
              }
            ],
            "Height": 100,
            "Length": 98
          },
          {
            "Type": "Leftover",
            "Height": 100,
            "Length": 1
          }
        ],
        "Height": 100,
        "Length": 100
      }
    },
    {
      "Object": 5,
      "Root": {
        "Type": "Structure",
        "Orientation": "H",
        "Children": [
          {
            "Type": "Structure",
            "Orientation": "V",
            "Children": [
              {
                "Type": "Structure",
                "Orientation": "H",
                "Children": [
                  {
                    "Type": "Item",
                    "Item": 39,
                    "Height": 89,
                    "Length": 14
                  },
                  {
                    "Type": "Leftover",
                    "Height": 1,
                    "Length": 14
                  }
                ],
                "Height": 90,
                "Length": 14
              },
              {
                "Type": "Structure",
                "Orientation": "H",
                "Children": [
                  {
                    "Type": "Item",
                    "Item": 64,
                    "Height": 88,
                    "Length": 41
                  },
                  {
                    "Type": "Leftover",
                    "Height": 2,
                    "Length": 41
                  }
                ],
                "Height": 90,
                "Length": 41
              },
              {
                "Type": "Structure",
                "Orientation": "H",
                "Children": [
                  {
                    "Type": "Item",
                    "Item": 73,
                    "Height": 82,
                    "Length": 44
                  },
                  {
                    "Type": "Leftover",
                    "Height": 8,
                    "Length": 44
                  }
                ],
                "Height": 90,
                "Length": 44
              }
            ],
            "Height": 90,
            "Length": 99
          }
        ],
        "Height": 90,
        "Length": 99
      }
    },
    {
      "Object": 1,
      "Root": {
        "Type": "Structure",
        "Orientation": "V",
        "Children": [
          {
            "Type": "Item",
            "Item": 18,
            "Height": 100,
            "Length": 48
          },
          {
            "Type": "Structure",
            "Orientation": "H",
            "Children": [
              {
                "Type": "Item",
                "Item": 41,
                "Height": 99,
                "Length": 42
              },
              {
                "Type": "Leftover",
                "Height": 1,
                "Length": 42
              }
            ],
            "Height": 100,
            "Length": 42
          },
          {
            "Type": "Structure",
            "Orientation": "H",
            "Children": [
              {
                "Type": "Item",
                "Item": 28,
                "Height": 68,
                "Length": 10
              },
              {
                "Type": "Leftover",
                "Height": 32,
                "Length": 10
              }
            ],
            "Height": 100,
            "Length": 10
          }
        ],
        "Height": 100,
        "Length": 100
      }
    },
    {
      "Object": 4,
      "Root": {
        "Type": "Structure",
        "Orientation": "H",
        "Children": [
          {
            "Type": "Structure",
            "Orientation": "V",
            "Children": [
              {
                "Type": "Structure",
                "Orientation": "H",
                "Children": [
                  {
                    "Type": "Item",
                    "Item": 43,
                    "Height": 94,
                    "Length": 24
                  },
                  {
                    "Type": "Leftover",
                    "Height": 4,
                    "Length": 24
                  }
                ],
                "Height": 98,
                "Length": 24
              },
              {
                "Type": "Structure",
                "Orientation": "H",
                "Children": [
                  {
                    "Type": "Structure",
                    "Orientation": "V",
                    "Children": [
                      {
                        "Type": "Item",
                        "Item": 9,
                        "Height": 78,
                        "Length": 37
                      },
                      {
                        "Type": "Structure",
                        "Orientation": "H",
                        "Children": [
                          {
                            "Type": "Item",
                            "Item": 20,
                            "Height": 76,
                            "Length": 14
                          },
                          {
                            "Type": "Leftover",
                            "Height": 2,
                            "Length": 14
                          }
                        ],
                        "Height": 78,
                        "Length": 14
                      }
                    ],
                    "Height": 78,
                    "Length": 51
                  },
                  {
                    "Type": "Structure",
                    "Orientation": "V",
                    "Children": [
                      {
                        "Type": "Item",
                        "Item": 80,
                        "Height": 20,
                        "Length": 42
                      },
                      {
                        "Type": "Leftover",
                        "Height": 20,
                        "Length": 9
                      }
                    ],
                    "Height": 20,
                    "Length": 51
                  }
                ],
                "Height": 98,
                "Length": 51
              }
            ],
            "Height": 98,
            "Length": 75
          }
        ],
        "Height": 98,
        "Length": 75
      }
    },
    {
      "Object": 5,
      "Root": {
        "Type": "Structure",
        "Orientation": "V",
        "Children": [
          {
            "Type": "Item",
            "Item": 2,
            "Height": 90,
            "Length": 20
          },
          {
            "Type": "Structure",
            "Orientation": "H",
            "Children": [
              {
                "Type": "Item",
                "Item": 29,
                "Height": 87,
                "Length": 15
              },
              {
                "Type": "Leftover",
                "Height": 3,
                "Length": 15
              }
            ],
            "Height": 90,
            "Length": 15
          },
          {
            "Type": "Structure",
            "Orientation": "H",
            "Children": [
              {
                "Type": "Structure",
                "Orientation": "V",
                "Children": [
                  {
                    "Type": "Item",
                    "Item": 4,
                    "Height": 77,
                    "Length": 63
                  },
                  {
                    "Type": "Leftover",
                    "Height": 77,
                    "Length": 1
                  }
                ],
                "Height": 77,
                "Length": 64
              },
              {
                "Type": "Leftover",
                "Height": 13,
                "Length": 64
              }
            ],
            "Height": 90,
            "Length": 64
          }
        ],
        "Height": 90,
        "Length": 99
      }
    },
    {
      "Object": 5,
      "Root": {
        "Type": "Structure",
        "Orientation": "H",
        "Children": [
          {
            "Type": "Structure",
            "Orientation": "V",
            "Children": [
              {
                "Type": "Structure",
                "Orientation": "H",
                "Children": [
                  {
                    "Type": "Item",
                    "Item": 69,
                    "Height": 86,
                    "Length": 47
                  },
                  {
                    "Type": "Leftover",
                    "Height": 4,
                    "Length": 47
                  }
                ],
                "Height": 90,
                "Length": 47
              },
              {
                "Type": "Structure",
                "Orientation": "H",
                "Children": [
                  {
                    "Type": "Item",
                    "Item": 61,
                    "Height": 84,
                    "Length": 37
                  },
                  {
                    "Type": "Leftover",
                    "Height": 6,
                    "Length": 37
                  }
                ],
                "Height": 90,
                "Length": 37
              },
              {
                "Type": "Structure",
                "Orientation": "H",
                "Children": [
                  {
                    "Type": "Item",
                    "Item": 40,
                    "Height": 83,
                    "Length": 15
                  },
                  {
                    "Type": "Leftover",
                    "Height": 7,
                    "Length": 15
                  }
                ],
                "Height": 90,
                "Length": 15
              }
            ],
            "Height": 90,
            "Length": 99
          }
        ],
        "Height": 90,
        "Length": 99
      }
    },
    {
      "Object": 5,
      "Root": {
        "Type": "Structure",
        "Orientation": "H",
        "Children": [
          {
            "Type": "Structure",
            "Orientation": "V",
            "Children": [
              {
                "Type": "Item",
                "Item": 19,
                "Height": 83,
                "Length": 40
              },
              {
                "Type": "Item",
                "Item": 46,
                "Height": 83,
                "Length": 20
              },
              {
                "Type": "Structure",
                "Orientation": "H",
                "Children": [
                  {
                    "Type": "Item",
                    "Item": 42,
                    "Height": 81,
                    "Length": 39
                  },
                  {
                    "Type": "Leftover",
                    "Height": 2,
                    "Length": 39
                  }
                ],
                "Height": 83,
                "Length": 39
              }
            ],
            "Height": 83,
            "Length": 99
          },
          {
            "Type": "Leftover",
            "Height": 7,
            "Length": 99
          }
        ],
        "Height": 90,
        "Length": 99
      }
    },
    {
      "Object": 1,
      "Root": {
        "Type": "Structure",
        "Orientation": "V",
        "Children": [
          {
            "Type": "Structure",
            "Orientation": "H",
            "Children": [
              {
                "Type": "Item",
                "Item": 15,
                "Height": 89,
                "Length": 100
              },
              {
                "Type": "Structure",
                "Orientation": "V",
                "Children": [
                  {
                    "Type": "Item",
                    "Item": 21,
                    "Height": 11,
                    "Length": 93
                  },
                  {
                    "Type": "Leftover",
                    "Height": 11,
                    "Length": 7
                  }
                ],
                "Height": 11,
                "Length": 100
              }
            ],
            "Height": 100,
            "Length": 100
          }
        ],
        "Height": 100,
        "Length": 100
      }
    },
    {
      "Object": 4,
      "Root": {
        "Type": "Structure",
        "Orientation": "V",
        "Children": [
          {
            "Type": "Structure",
            "Orientation": "H",
            "Children": [
              {
                "Type": "Item",
                "Item": 67,
                "Height": 83,
                "Length": 27
              },
              {
                "Type": "Item",
                "Item": 5,
                "Height": 12,
                "Length": 27
              },
              {
                "Type": "Leftover",
                "Height": 3,
                "Length": 27
              }
            ],
            "Height": 98,
            "Length": 27
          },
          {
            "Type": "Structure",
            "Orientation": "H",
            "Children": [
              {
                "Type": "Item",
                "Item": 51,
                "Height": 92,
                "Length": 28
              },
              {
                "Type": "Leftover",
                "Height": 6,
                "Length": 28
              }
            ],
            "Height": 98,
            "Length": 28
          },
          {
            "Type": "Structure",
            "Orientation": "H",
            "Children": [
              {
                "Type": "Structure",
                "Orientation": "V",
                "Children": [
                  {
                    "Type": "Item",
                    "Item": 13,
                    "Height": 92,
                    "Length": 10
                  },
                  {
                    "Type": "Structure",
                    "Orientation": "H",
                    "Children": [
                      {
                        "Type": "Item",
                        "Item": 70,
                        "Height": 91,
                        "Length": 1
                      },
                      {
                        "Type": "Leftover",
                        "Height": 1,
                        "Length": 1
                      }
                    ],
                    "Height": 92,
                    "Length": 1
                  },
                  {
                    "Type": "Structure",
                    "Orientation": "H",
                    "Children": [
                      {
                        "Type": "Item",
                        "Item": 60,
                        "Height": 84,
                        "Length": 8
                      },
                      {
                        "Type": "Leftover",
                        "Height": 8,
                        "Length": 8
                      }
                    ],
                    "Height": 92,
                    "Length": 8
                  },
                  {
                    "Type": "Leftover",
                    "Height": 92,
                    "Length": 1
                  }
                ],
                "Height": 92,
                "Length": 20
              },
              {
                "Type": "Leftover",
                "Height": 6,
                "Length": 20
              }
            ],
            "Height": 98,
            "Length": 20
          }
        ],
        "Height": 98,
        "Length": 75
      }
    }
  ]
}